{
  "node_id": "1:4217",
  "format": "react_tsx",
  "asset_urls": {
    "imgRectangle161124081": "https://www.figma.com/api/mcp/asset/7cca59ab-6605-43d7-aa41-dc60dd1031fd"
  },
  "code": "const imgRectangle161124081 = \"https://www.figma.com/api/mcp/asset/7cca59ab-6605-43d7-aa41-dc60dd1031fd\";\n\nexport default function Frame1171281881() {\n  return (\n    <div className=\"bg-white border border-[rgba(211,211,211,0.6)] border-solid relative rounded-[35px] size-full\" data-node-id=\"1:4217\">\n      <div className=\"absolute h-[362px] left-[-1px] top-[-1px] w-[1308px]\" data-node-id=\"1:4218\" />\n      <div className=\"absolute h-[362px] left-[-1px] rounded-bl-[35px] rounded-tl-[35px] top-[-1px] w-[447px]\" data-node-id=\"1:4219\">\n        <div className=\"absolute inset-0 overflow-hidden pointer-events-none rounded-bl-[35px] rounded-tl-[35px]\">\n          <img alt=\"\" className=\"absolute h-[138.75%] left-[-0.77%] max-w-none top-0 w-[146.29%]\" src={imgRectangle161124081} />\n        </div>\n      </div>\n      <div className=\"absolute contents left-[486px] top-[25px]\" data-node-id=\"1:4220\">\n        <div className=\"-translate-y-1/2 [word-break:break-word] absolute flex flex-col font-['Host_Grotesk:Bold',sans-serif] justify-center leading-[0] left-[487px] not-italic text-[40px] text-black top-[55px] tracking-[-0.56px] whitespace-nowrap\" data-node-id=\"1:4221\">\n          <p className=\"leading-[58px]\">Yoga for Sciatica</p>\n        </div>\n        <div className=\"-translate-y-1/2 [word-break:break-word] absolute flex flex-col font-['DM_Sans:Regular',sans-serif] font-normal justify-center leading-[0] left-[487px] text-[#4b4b4b] text-[17px] top-[111px] w-[597px]\" data-node-id=\"1:4222\" style={{ fontVariationSettings: \"'opsz' 14\" }}>\n          <p className=\"leading-[27px]\">Pay once. Access 25 expert-led video lessons at your own pace, forever. From beginner inversions to advanced flows.</p>\n        </div>\n        <div className=\"absolute content-stretch flex items-center left-[487px] top-[160px]\" data-node-id=\"1:4223\">\n          <div className=\"content-stretch flex items-center relative shrink-0\" data-node-id=\"1:4224\">\n            <div className=\"[word-break:break-word] h-[90px] leading-[normal] not-italic relative shrink-0 w-[351px] whitespace-nowrap\" data-node-id=\"1:4225\" data-name=\"hero-stats\">\n              <div className=\"absolute bg-white border border-[#e2e2e2] border-solid content-stretch flex flex-col h-[89.546px] items-center justify-center left-[-0.04%] opacity-82 p-px right-[72.57%] rounded-[17px] top-0\" data-node-id=\"1:4226\" data-name=\"stat\">\n                <p className=\"font-['Inter:Medium',sans-serif] font-medium mb-[-0.011px] relative shrink-0 text-[#009877] text-[25.257px]\" data-node-id=\"1:4227\">\n                  25\n                </p>\n                <p className=\"font-['Inter:Regular',sans-serif] font-normal relative shrink-0 text-[12.628px] text-[rgba(13,13,13,0.65)] tracking-[0.574px] uppercase\" data-node-id=\"1:4228\">\n                  Videos\n                </p>\n              </div>\n              <div className=\"absolute bg-white border border-[#e2e2e2] border-solid content-stretch flex flex-col h-[89.546px] items-center justify-center left-[30.85%] opacity-82 pl-[3.296px] pr-px py-px right-[37.75%] rounded-[17px] top-0\" data-node-id=\"1:4229\" data-name=\"stat\">\n                <p className=\"font-['Inter:Medium',sans-serif] font-medium mb-[-0.011px] relative shrink-0 text-[#009877] text-[25.257px]\" data-node-id=\"1:4230\">\n                  8h\n                </p>\n                <p className=\"font-['Inter:Regular',sans-serif] font-normal relative shrink-0 text-[12.628px] text-[rgba(13,13,13,0.65)] tracking-[0.574px] uppercase\" data-node-id=\"1:4231\">\n                  Content\n                </p>\n              </div>\n              <div className=\"absolute bg-white border border-[#e2e2e2] border-solid content-stretch flex flex-col h-[89.546px] items-center justify-center left-[65.67%] opacity-82 pl-[3.296px] pr-px py-px right-[6.2%] rounded-[17px] top-0\" data-node-id=\"1:4232\" data-name=\"stat\">\n                <p className=\"font-['Inter:Medium',sans-serif] font-medium mb-[-0.011px] relative shrink-0 text-[#009877] text-[25.257px]\" data-node-id=\"1:4233\">\n                  ∞\n                </p>\n                <p className=\"font-['Inter:Regular',sans-serif] font-normal relative shrink-0 text-[12.628px] text-[rgba(13,13,13,0.65)] tracking-[0.574px] uppercase\" data-node-id=\"1:4234\">\n                  Access\n                </p>\n              </div>\n            </div>\n          </div>\n        </div>\n      </div>\n      <div className=\"absolute bg-[#8ee0ce] content-stretch flex h-[44px] items-center justify-center left-[486px] p-[15px] rounded-[23px] top-[288px] w-[241px]\" data-node-id=\"1:4235\" data-name=\"Button\">\n        <div className=\"[word-break:break-word] flex flex-col font-['DM_Sans:SemiBold',sans-serif] font-semibold justify-center leading-[0] relative shrink-0 text-[#243a42] text-[15px] text-center whitespace-nowrap\" data-node-id=\"1:4236\" style={{ fontVariationSettings: \"'opsz' 14\" }}>\n          <p className=\"leading-[normal]\">Purchase now</p>\n        </div>\n      </div>\n      <div className=\"-translate-y-1/2 [word-break:break-word] absolute flex flex-col font-['Host_Grotesk:Bold',sans-serif] justify-center leading-[0] left-[1193px] not-italic text-[30px] text-black top-[54px] tracking-[-0.56px] whitespace-nowrap\" data-node-id=\"1:4237\">\n        <p className=\"leading-[58px]\">₹499</p>\n      </div>\n      <div className=\"absolute contents left-[995px] top-[252px]\" data-node-id=\"1:4238\">\n        <div className=\"absolute content-stretch flex flex-col gap-[9.662px] h-[71.949px] items-start left-[996px] top-[253px] w-[275px]\" data-node-id=\"1:4239\">\n          <div className=\"content-stretch flex gap-[15.608px] items-center opacity-72 relative shrink-0\" data-node-id=\"1:4240\">\n            <div className=\"[word-break:break-word] flex flex-col font-['Instrument_Sans:SemiBold',sans-serif] font-semibold justify-center leading-[0] relative shrink-0 text-[8.919px] text-black tracking-[5.2027px] uppercase whitespace-nowrap\" data-node-id=\"1:4241\" style={{ fontVariationSettings: \"'wdth' 100\" }}>\n              <p className=\"leading-[normal]\">workshop starting in</p>\n            </div>\n            <div className=\"bg-black h-[0.743px] opacity-40 relative shrink-0 w-[31.959px]\" data-node-id=\"1:4242\" data-name=\"Horizontal Divider\" />\n          </div>\n          <div className=\"[word-break:break-word] content-stretch flex gap-[44.58px] items-center leading-[0] relative shrink-0 text-black w-full whitespace-nowrap\" data-node-id=\"1:4243\">\n            <div className=\"grid-cols-[max-content] grid-rows-[max-content] inline-grid place-items-start relative shrink-0\" data-node-id=\"1:4244\">\n              <div className=\"col-1 flex flex-col font-['Instrument_Sans:SemiBold',sans-serif] font-semibold justify-center ml-0 mt-0 relative row-1 text-[29.541px] tracking-[2.6573px] uppercase\" data-node-id=\"1:4245\" style={{ fontVariationSettings: \"'wdth' 100\" }}>\n                <p className=\"leading-[normal]\">02</p>\n              </div>\n              <div className=\"col-1 flex flex-col font-['SF_Pro_Display:Regular',sans-serif] justify-center ml-[7.52px] mt-[33.3px] not-italic relative row-1 text-[11.816px] tracking-[0.043px]\" data-node-id=\"1:4246\">\n                <p className=\"leading-[17.725px]\">Days</p>\n              </div>\n            </div>\n            <div className=\"grid-cols-[max-content] grid-rows-[max-content] inline-grid place-items-start relative shrink-0\" data-node-id=\"1:4247\">\n              <div className=\"col-1 flex flex-col font-['SF_Pro_Display:Regular',sans-serif] justify-center ml-[1.61px] mt-[33.3px] not-italic relative row-1 text-[11.816px] tracking-[0.043px]\" data-node-id=\"1:4248\">\n                <p className=\"leading-[17.725px]\">Hours</p>\n              </div>\n              <div className=\"col-1 flex flex-col font-['Instrument_Sans:SemiBold',sans-serif] font-semibold justify-center ml-0 mt-0 relative row-1 text-[29.541px] tracking-[2.6573px] uppercase\" data-node-id=\"1:4249\" style={{ fontVariationSettings: \"'wdth' 100\" }}>\n                <p className=\"leading-[normal]\">18</p>\n              </div>\n            </div>\n            <div className=\"grid-cols-[max-content] grid-rows-[max-content] inline-grid place-items-start relative shrink-0\" data-node-id=\"1:4250\">\n              <div className=\"col-1 flex flex-col font-['SF_Pro_Display:Regular',sans-serif] justify-center ml-[6.98px] mt-[33.3px] not-italic opacity-80 relative row-1 text-[11.816px] tracking-[0.043px]\" data-node-id=\"1:4251\">\n                <p className=\"leading-[17.725px]\">Mins</p>\n              </div>\n              <div className=\"col-1 flex flex-col font-['Instrument_Sans:SemiBold',sans-serif] font-semibold justify-center ml-0 mt-0 relative row-1 text-[29.541px] tracking-[2.6573px] uppercase\" data-node-id=\"1:4252\" style={{ fontVariationSettings: \"'wdth' 100\" }}>\n                <p className=\"leading-[normal]\">38</p>\n              </div>\n            </div>\n            <div className=\"grid-cols-[max-content] grid-rows-[max-content] inline-grid place-items-start relative shrink-0\" data-node-id=\"1:4253\">\n              <div className=\"col-1 flex flex-col font-['SF_Pro_Display:Regular',sans-serif] justify-center ml-[5.37px] mt-[33.3px] not-italic opacity-80 relative row-1 text-[11.816px] tracking-[0.043px]\" data-node-id=\"1:4254\">\n                <p className=\"leading-[17.725px]\">Secs</p>\n              </div>\n              <div className=\"col-1 flex flex-col font-['Instrument_Sans:Regular',sans-serif] font-normal justify-center ml-0 mt-0 opacity-80 relative row-1 text-[29.541px] tracking-[2.6573px] uppercase\" data-node-id=\"1:4255\" style={{ fontVariationSettings: \"'wdth' 100\" }}>\n                <p className=\"leading-[normal]\">19</p>\n              </div>\n            </div>\n          </div>\n        </div>\n      </div>\n    </div>\n  );\n}"
}
