{
  "source": {
    "nodeId": "91:16473",
    "fileKey": "eqaofBeNUhOUISevtRfOpT",
    "extracted_at": "2026-05-21T00:00:00Z",
    "page_name": "04 — Component Token Map"
  },
  "components": [
    {
      "id": "doc.page-header",
      "figma_id": "91:16474",
      "name": "Doc Page Header",
      "kind": "documentation",
      "category": "doc-shell",
      "description": "Header strip: brand wordmark 'Bodhi School of Yoga' + title 'Design System' + subtitle 'Token reference for developers — colors, typography, spacing & usage guidelines'.",
      "size": {"width": 1440, "height": 160},
      "children": ["91:16475", "91:16476", "91:16477", "91:16478", "91:16479"]
    },
    {
      "id": "doc.section-01-color-tokens",
      "figma_id": "91:16480",
      "name": "Section 01 — Color Tokens (reference)",
      "kind": "documentation",
      "category": "doc-section",
      "description": "Re-included from page 91:15377. 15 color swatch cards in 4 groups (Brand, Text, Surface, Border). Source for color tokens already captured in node_91-15377 extraction.",
      "duplicates_of": ["91:15377"]
    },
    {
      "id": "doc.section-02-typography",
      "figma_id": "91:16569",
      "name": "Section 02 — Typography (reference)",
      "kind": "documentation",
      "category": "doc-section",
      "description": "Re-included typography table. Two typeface specimen cards (Host Grotesk, DM Sans) + table of 9 type styles (H1..H5, subtext-3/2/1, mini-text). Same content as page 91:15743.",
      "duplicates_of": ["91:15743"]
    },
    {
      "id": "doc.section-03-spacing-radius",
      "figma_id": "91:16682",
      "name": "Section 03 — Spacing & Border Radius (reference)",
      "kind": "documentation",
      "category": "doc-section",
      "description": "Re-included 4px-base spacing scale (12 chips xs..6xl) + border radius chips (none/xs/sm/md/lg/xl/full). Same content as page 91:16108.",
      "duplicates_of": ["91:16108"]
    },
    {
      "id": "doc.section-04-component-token-map",
      "figma_id": "91:16473",
      "name": "Section 04 — Component Token Map",
      "kind": "documentation",
      "category": "doc-section",
      "description": "UNIQUE TO THIS PAGE. Table mapping each UI component to its concrete design tokens. Columns: Component, Fill, Text, Border, Radius, Typography, States.",
      "table": {
        "header": {
          "figma_id": "91:16766",
          "columns": ["Component", "Fill", "Text", "Border", "Radius", "Typography", "States"]
        },
        "rows": [
          {
            "figma_id": "91:16774",
            "component": "Primary Button",
            "fill": "brand-primary",
            "text": "text-inverse",
            "border": "—",
            "radius": "8px",
            "typography": "subtext-1 SemiBold",
            "states": "Hover: brand-shade · Disabled: 40% opacity"
          },
          {
            "figma_id": "91:16782",
            "component": "Ghost Button",
            "fill": "transparent",
            "text": "text-brand",
            "border": "brand-primary 1px",
            "radius": "8px",
            "typography": "subtext-1 SemiBold",
            "states": "Hover: brand lite bg"
          },
          {
            "figma_id": "91:16790",
            "component": "Card",
            "fill": "Surface-1",
            "text": "text-secondary",
            "border": "border-2 1px",
            "radius": "12px",
            "typography": "H5 title · subtext-1 body",
            "states": "Hover: Surface-2 · shadow"
          },
          {
            "figma_id": "91:16799",
            "component": "Input Field",
            "fill": "Surface-1",
            "text": "text-secondary",
            "border": "border-3 1px",
            "radius": "8px",
            "typography": "subtext-1 Regular",
            "states": "Focus: brand-primary border"
          },
          {
            "figma_id": "91:16806",
            "component": "Badge / Tag",
            "fill": "brand lite",
            "text": "text-brand",
            "border": "—",
            "radius": "999px",
            "typography": "mini-text",
            "states": "—"
          },
          {
            "figma_id": "91:16814",
            "component": "Nav Link",
            "fill": "transparent",
            "text": "text-secondary",
            "border": "—",
            "radius": "—",
            "typography": "subtext-1 Regular",
            "states": "Active: text-brand + underline"
          },
          {
            "figma_id": "91:16822",
            "component": "Section Heading",
            "fill": "transparent",
            "text": "text-primary",
            "border": "—",
            "radius": "—",
            "typography": "H2 or H3",
            "states": "—"
          }
        ]
      }
    }
  ],
  "ui_components_mapped": [
    {"id": "primary-button", "type": "Button.primary", "figma_id": "91:16774"},
    {"id": "ghost-button", "type": "Button.ghost", "figma_id": "91:16782"},
    {"id": "card", "type": "Card", "figma_id": "91:16790"},
    {"id": "input-field", "type": "Input.text", "figma_id": "91:16799"},
    {"id": "badge-tag", "type": "Badge", "figma_id": "91:16806"},
    {"id": "nav-link", "type": "Nav.link", "figma_id": "91:16814"},
    {"id": "section-heading", "type": "Heading.section", "figma_id": "91:16822"}
  ],
  "counts": {
    "doc_sections": 5,
    "ui_components_mapped": 7,
    "table_rows": 7,
    "table_columns": 7
  }
}
